mkdocs_variable_randomizer_plugin/__init__.py
mkdocs_variable_randomizer_plugin-0.0.1.dist-info/licenses/LICENSE
mkdocs_variable_randomizer_plugin-0.0.1.dist-info/METADATA
mkdocs_variable_randomizer_plugin-0.0.1.dist-info/WHEEL
mkdocs_variable_randomizer_plugin-0.0.1.dist-info/entry_points.txt
mkdocs_variable_randomizer_plugin-0.0.1.dist-info/top_level.txt
mkdocs_variable_randomizer_plugin-0.0.1.dist-info/RECORD
