Metadata-Version: 2.4
Name: mkdocs-variable-randomizer-plugin
Version: 0.0.1
Summary: Replace some variables in snippets with random names
Home-page: https://github.com/six-two/mkdocs-variable-randomizer-plugin
Author: six-two
Author-email: six-two <pip@six-two.dev>
License-Expression: MIT
Project-URL: Homepage, https://github.com/six-two/mkdocs-variable-randomizer-plugin
Project-URL: Issues, https://github.com/six-two/mkdocs-variable-randomizer-plugin/issues
Classifier: Programming Language :: Python :: 3
Classifier: Operating System :: OS Independent
Requires-Python: >=3.9
License-File: LICENSE
Dynamic: license-file
